secured/__init__.py
secured/attribute.py
secured/log_manager.py
secured/secure.py
secured/secured.py
secured-0.1.6.dist-info/LICENSE
secured-0.1.6.dist-info/METADATA
secured-0.1.6.dist-info/WHEEL
secured-0.1.6.dist-info/RECORD
