Metadata-Version: 2.1
Name: secured
Version: 0.1.6
Summary: 
License: MIT
Author: Joao Paulo Euko
Requires-Python: >=3.10,<4.0
Classifier: License :: OSI Approved :: MIT License
Classifier: Programming Language :: Python :: 3
Classifier: Programming Language :: Python :: 3.10
Classifier: Programming Language :: Python :: 3.11
Classifier: Programming Language :: Python :: 3.12
Requires-Dist: pyyaml (>=6.0.1,<7.0.0)
